Metadata-Version: 1.0
Name: i3-workspace-rollback
Version: 1.1
Summary: i3 plugin for rollback to last focused workspace
Home-page: https://github.com/alexrochas/i3-workspace-rollback
Author: Alex Rocha
Author-email: alex.rochas@yahoo.com.br
License: MIT
Platform: UNKNOWN
